ricco/__init__.py
ricco/base.py
ricco/local.py
ricco/etl/__init__.py
ricco/etl/data_reporter.py
ricco/etl/entropy.py
ricco/etl/extract.py
ricco/etl/file.py
ricco/etl/graph.py
ricco/etl/load.py
ricco/etl/stat.py
ricco/etl/transformer.py
ricco/fs/__init__.py
ricco/fs/oss.py
ricco/fs/sftp.py
ricco/fs/util.py
ricco/geocode/__init__.py
ricco/geocode/amap.py
ricco/geocode/baidu.py
ricco/geocode/geocode.py
ricco/geocode/parallel.py
ricco/geocode/request.py
ricco/geocode/util.py
ricco/geometry/__init__.py
ricco/geometry/coord_trans.py
ricco/geometry/df.py
ricco/geometry/topology.py
ricco/geometry/util.py
ricco/resource/__init__.py
ricco/resource/area_code.py
ricco/resource/bd_region.csv
ricco/resource/bd_region.py
ricco/resource/city_id.py
ricco/resource/crs.py
ricco/resource/epsg_code.py
ricco/resource/names.py
ricco/resource/patterns.py
ricco/resource/phone_number.py
ricco/resource/postcode.csv
ricco/resource/postcode.py
ricco/resource/stopwords.py
ricco/resource/stopwords.txt
ricco/util/__init__.py
ricco/util/address_tools.py
ricco/util/assertion.py
ricco/util/base.py
ricco/util/building_address.py
ricco/util/decorator.py
ricco/util/district.py
ricco/util/docx.py
ricco/util/dt.py
ricco/util/exception.py
ricco/util/id_generator.py
ricco/util/id_number.py
ricco/util/kdtree.py
ricco/util/media.py
ricco/util/os.py
ricco/util/phone_number.py
ricco/util/postcode.py
ricco/util/random.py
ricco/util/strings.py
ricco/util/util.py
ricco-2.0.0.dist-info/METADATA
ricco-2.0.0.dist-info/WHEEL
ricco-2.0.0.dist-info/top_level.txt
ricco-2.0.0.dist-info/RECORD
