Metadata-Version: 2.4
Name: ricco
Version: 2.0.0
Summary: A handy ETL&GEOM kit
Home-page: https://github.com/Ricco1010/ricco
Author: Ricco Wang
Author-email: wyk_0610@163.com
Platform: any
Classifier: Development Status :: 3 - Alpha
Classifier: Intended Audience :: Developers
Classifier: Natural Language :: English
Classifier: Operating System :: OS Independent
Classifier: Programming Language :: Python
Classifier: Programming Language :: Python :: 3
Classifier: Topic :: Software Development :: Libraries
Requires-Dist: fuzzywuzzy==0.18.0
Requires-Dist: geojson<3
Requires-Dist: geopandas<1,>=0.10
Requires-Dist: numpy<2,>=1
Requires-Dist: pandarallel==1.6.5
Requires-Dist: pandas>=1
Requires-Dist: pyarrow
Requires-Dist: pyahocorasick>=2
Requires-Dist: python-dateutil
Requires-Dist: python-Levenshtein>=0.25.0
Requires-Dist: requests>=2.7
Requires-Dist: shapely>=1.7
Requires-Dist: tqdm>=4.62.0
Dynamic: author
Dynamic: author-email
Dynamic: classifier
Dynamic: description
Dynamic: description-content-type
Dynamic: home-page
Dynamic: platform
Dynamic: requires-dist
Dynamic: summary
